rpdk/go/__init__.py
rpdk/go/codegen.py
rpdk/go/parser.py
rpdk/go/resolver.py
rpdk/go/utils.py
rpdk/go/version.py
rpdk/go/data/go.gitignore
rpdk/go/templates/Makefile
rpdk/go/templates/README.md
rpdk/go/templates/config.go.tple
rpdk/go/templates/go.mod.tple
rpdk/go/templates/main.go.tple
rpdk/go/templates/makebuild
rpdk/go/templates/stubHandler.go.tple
rpdk/go/templates/types.go.tple
cloudformation_cli_go_plugin-2.2.0.dist-info/LICENSE
cloudformation_cli_go_plugin-2.2.0.dist-info/METADATA
cloudformation_cli_go_plugin-2.2.0.dist-info/WHEEL
cloudformation_cli_go_plugin-2.2.0.dist-info/entry_points.txt
cloudformation_cli_go_plugin-2.2.0.dist-info/top_level.txt
cloudformation_cli_go_plugin-2.2.0.dist-info/zip-safe
cloudformation_cli_go_plugin-2.2.0.dist-info/RECORD
