Metadata-Version: 2.1
Name: cloudformation-cli-go-plugin
Version: 2.2.0
Home-page: https://github.com/aws-cloudformation/cloudformation-cli-go-plugin/
Author: Amazon Web Services
Author-email: aws-cloudformation-developers@amazon.com
License: Apache License 2.0
Keywords: Amazon Web Services AWS CloudFormation
Classifier: Development Status :: 4 - Beta
Classifier: Intended Audience :: Developers
Classifier: License :: OSI Approved :: Apache Software License
Classifier: Natural Language :: English
Classifier: Topic :: Software Development :: Build Tools
Classifier: Topic :: Software Development :: Code Generators
Classifier: Operating System :: OS Independent
Classifier: Programming Language :: Python :: 3 :: Only
Classifier: Programming Language :: Python :: 3.8
Classifier: Programming Language :: Python :: 3.9
Classifier: Programming Language :: Python :: 3.10
Classifier: Programming Language :: Python :: 3.11
Requires-Python: >=3.8
License-File: LICENSE
Requires-Dist: cloudformation-cli >=0.1.14
Requires-Dist: semver >=2.9.0
